cdsetool/__init__.py
cdsetool/_processing.py
cdsetool/cli.py
cdsetool/credentials.py
cdsetool/download.py
cdsetool/logger.py
cdsetool/monitor.py
cdsetool/py.typed
cdsetool/query.py
cdsetool-0.2.13.dist-info/LICENSE
cdsetool-0.2.13.dist-info/METADATA
cdsetool-0.2.13.dist-info/WHEEL
cdsetool-0.2.13.dist-info/entry_points.txt
cdsetool-0.2.13.dist-info/top_level.txt
cdsetool-0.2.13.dist-info/RECORD
