Metadata-Version: 2.1
Name: cdsetool
Version: 0.2.13
Summary: Tools & CLI for interacting with CDSE product APIs
Author-email: Jacob Vejby <javej@sdfi.dk>
Project-URL: Homepage, https://github.com/CDSETool/CDSETool
Project-URL: Bug Tracker, https://github.com/CDSETool/CDSETool/issues
Classifier: Programming Language :: Python :: 3
Classifier: Operating System :: OS Independent
Requires-Python: >=3.9
License-File: LICENSE
Requires-Dist: typer <1,>=0.9
Requires-Dist: rich <14,>=13.6
Requires-Dist: requests <3,>=2.28.1
Requires-Dist: pyjwt[crypto] <2.10,>=2.8
Requires-Dist: geopandas >=0.13.2
Provides-Extra: test
Requires-Dist: pylint ==3.3.1 ; extra == 'test'
Requires-Dist: pytest ==8.3.3 ; extra == 'test'
Requires-Dist: pytest-cov ==5.0.0 ; extra == 'test'
Requires-Dist: requests-mock ==1.12.1 ; extra == 'test'
Requires-Dist: ruff ==0.6.6 ; extra == 'test'
Requires-Dist: pytest-mock ==3.14.0 ; extra == 'test'
